[
    {
        "name": "core/group",
        "attributes": {
            "align": "full",
            "style": {
                "spacing": {
                    "padding": {
                        "top": "80px"
                    }
                },
                "color": []
            },
            "layout": {
                "wideSize": "1200px",
                "contentSize": "700px",
                "type": "constrained"
            }
        },
        "innerBlocks": [
            {
                "name": "core/columns",
                "attributes": {
                    "align": "wide"
                },
                "innerBlocks": [
                    {
                        "name": "core/column",
                        "innerBlocks": [
                            {
                                "name": "core/heading",
                                "attributes": {
                                    "textAlign": "center",
                                    "content": "Gallery ",
                                    "textColor": "luminous-vivid-amber",
                                    "fontSize": "medium",
                                    "style": {
                                        "typography": {
                                            "fontStyle": "normal",
                                            "fontWeight": "400"
                                        },
                                        "color": []
                                    }
                                }
                            },
                            {
                                "name": "core/heading",
                                "attributes": {
                                    "textAlign": "center",
                                    "content": "Gallery Three Column Masonry",
                                    "fontSize": "x-large",
                                    "style": {
                                        "typography": {
                                            "fontStyle": "normal",
                                            "fontWeight": "600"
                                        },
                                        "color": {
                                            "text": "#001f38"
                                        }
                                    }
                                }
                            }
                        ]
                    }
                ]
            },
            {
                "name": "core/paragraph",
                "attributes": {
                    "align": "center",
                    "content": "Lorem ipsum dolor sit amet, consectetur adipiscing elit, sed do eiusmod tempor incididunt ut labore et dolore magna aliqua. Ut enim ad minim veniam quis nostrud exercitation",
                    "style": {
                        "color": {
                            "text": "#5d6c79"
                        },
                        "typography": {
                            "fontSize": "16px"
                        }
                    }
                }
            }
        ]
    },
    {
        "name": "core/group",
        "attributes": {
            "align": "full",
            "gradient": "pale-ocean",
            "style": {
                "spacing": {
                    "padding": {
                        "top": "40px",
                        "bottom": "40px",
                        "right": "20px",
                        "left": "20px"
                    },
                    "margin": {
                        "top": "80px"
                    }
                }
            },
            "layout": {
                "wideSize": "1200px"
            }
        },
        "innerBlocks": [
            {
                "name": "core/columns",
                "attributes": {
                    "verticalAlignment": "top",
                    "align": "wide"
                },
                "innerBlocks": [
                    {
                        "name": "core/column",
                        "attributes": {
                            "verticalAlignment": "top"
                        },
                        "innerBlocks": [
                            {
                                "name": "core/gallery",
                                "attributes": {
                                    "columns": 1,
                                    "linkTo": "none"
                                },
                                "innerBlocks": [
                                    {
                                        "name": "core/image",
                                        "attributes": {
                                            "url": "https://img.rawpixel.com/s3fs-private/rawpixel_images/website_content/pd15-337-num.jpg?w=1200&h=1200&fit=clip&crop=default&dpr=1&q=75&vib=3&con=3&usm=15&cs=srgb&bg=F4F4F3&ixlib=js-2.2.1&s=279e95c74c89319f73e18450016f20d8",
                                            "sizeSlug": "full",
                                            "linkDestination": "none"
                                        }
                                    },
                                    {
                                        "name": "core/image",
                                        "attributes": {
                                            "url": "https://img.rawpixel.com/s3fs-private/rawpixel_images/website_content/pd17-262-num-phaethon-lepturus-tropic-bird.jpg?w=1200&h=1200&fit=clip&crop=default&dpr=1&q=75&vib=3&con=3&usm=15&cs=srgb&bg=F4F4F3&ixlib=js-2.2.1&s=2ae17802332cec2466acce6a9f549dca"
                                        }
                                    }
                                ]
                            }
                        ]
                    },
                    {
                        "name": "core/column",
                        "attributes": {
                            "verticalAlignment": "top"
                        },
                        "innerBlocks": [
                            {
                                "name": "core/gallery",
                                "attributes": {
                                    "columns": 1,
                                    "linkTo": "none"
                                },
                                "innerBlocks": [
                                    {
                                        "name": "core/image",
                                        "attributes": {
                                            "url": "https://img.rawpixel.com/s3fs-private/rawpixel_images/website_content/pd17-236-num-nycticorax-nycticorax-night-heron-or-qua-bird.jpg?w=1200&h=1200&fit=clip&crop=default&dpr=1&q=75&vib=3&con=3&usm=15&cs=srgb&bg=F4F4F3&ixlib=js-2.2.1&s=1868293dccbd3ce8f963aabfa8d75729",
                                            "sizeSlug": "full",
                                            "linkDestination": "none"
                                        }
                                    },
                                    {
                                        "name": "core/image",
                                        "attributes": {
                                            "url": "https://img.rawpixel.com/s3fs-private/rawpixel_images/website_content/pd17-356-num-circus-cyaneus-marsh-hawk.jpg?w=1200&h=1200&fit=clip&crop=default&dpr=1&q=75&vib=3&con=3&usm=15&cs=srgb&bg=F4F4F3&ixlib=js-2.2.1&s=46e744c57de4d1703eb73bb245672f08",
                                            "sizeSlug": "full",
                                            "linkDestination": "none"
                                        }
                                    }
                                ]
                            }
                        ]
                    },
                    {
                        "name": "core/column",
                        "attributes": {
                            "verticalAlignment": "top"
                        },
                        "innerBlocks": [
                            {
                                "name": "core/gallery",
                                "attributes": {
                                    "columns": 1,
                                    "linkTo": "none"
                                },
                                "innerBlocks": [
                                    {
                                        "name": "core/image",
                                        "attributes": {
                                            "url": "https://img.rawpixel.com/s3fs-private/rawpixel_images/website_content/pd17-074-num-passerina-cyanea-indigo-bird.jpg?w=1200&h=1200&fit=clip&crop=default&dpr=1&q=75&vib=3&con=3&usm=15&cs=srgb&bg=F4F4F3&ixlib=js-2.2.1&s=e20dc4acd5cf6a73b17b2dab46d5d28d",
                                            "sizeSlug": "full",
                                            "linkDestination": "none"
                                        }
                                    },
                                    {
                                        "name": "core/image",
                                        "attributes": {
                                            "url": "https://img.rawpixel.com/s3fs-private/rawpixel_images/website_content/pd15-588-num.jpg?w=1200&h=1200&fit=clip&crop=default&dpr=1&q=75&vib=3&con=3&usm=15&cs=srgb&bg=F4F4F3&ixlib=js-2.2.1&s=40aecd4d943bbfc9c7438474f65443b9",
                                            "sizeSlug": "full",
                                            "linkDestination": "none"
                                        }
                                    }
                                ]
                            }
                        ]
                    }
                ]
            }
        ]
    }
]